smartlink_local/__init__.py
smartlink_local/smartlink.py
smartlink_local-0.0.67.dist-info/METADATA
smartlink_local-0.0.67.dist-info/WHEEL
smartlink_local-0.0.67.dist-info/top_level.txt
smartlink_local-0.0.67.dist-info/RECORD
