Metadata-Version: 2.4
Name: smartlink-local
Version: 0.0.67
Summary: PyPI Package for Circles smart link Python
Home-page: https://github.com/circles-zone/smartlink-local-python-package
Author: Circles
Author-email: info@circlez.ai
Classifier: Programming Language :: Python :: 3
Classifier: License :: Other/Proprietary License
Classifier: Operating System :: OS Independent
Requires-Dist: logger-local>=0.0.136
Requires-Dist: message-local>=0.0.142
Requires-Dist: queue-worker-local>=0.0.37
Requires-Dist: database-mysql-local>=0.0.290
Requires-Dist: python-sdk-remote
Dynamic: author
Dynamic: author-email
Dynamic: classifier
Dynamic: description
Dynamic: description-content-type
Dynamic: home-page
Dynamic: requires-dist
Dynamic: summary
